objectipy/__init__.py
objectipy-0.0.1a1.dist-info/DESCRIPTION.rst
objectipy-0.0.1a1.dist-info/METADATA
objectipy-0.0.1a1.dist-info/RECORD
objectipy-0.0.1a1.dist-info/WHEEL
objectipy-0.0.1a1.dist-info/metadata.json
objectipy-0.0.1a1.dist-info/top_level.txt
objectipy-0.0.1a1.dist-info/zip-safe
